[{"id":161,"baseurl":"","url":"/p/example_interfaces/github-ros2-example_interfaces#ardent","last_commit_time":"2017-12-09","tags":"example interfaces","name":"example_interfaces","repo_name":"example_interfaces","released":"is:released","unreleased":"is:unreleased","version":"0.4.0","description":"Contains message and service definitions used by the examples.","maintainers":"Dirk Thomas","authors":"","distro":"ardent","instance":"github-ros2-example_interfaces","readme":""},{"id":173,"baseurl":"","url":"/p/examples_rclcpp_minimal_client/github-ros2-examples#ardent","last_commit_time":"2017-12-09","tags":"examples rclcpp minimal client","name":"examples_rclcpp_minimal_client","repo_name":"examples","released":"is:released","unreleased":"is:unreleased","version":"0.4.0","description":"Examples of minimal service clients","maintainers":"Morgan Quigley","authors":"","distro":"ardent","instance":"github-ros2-examples","readme":""},{"id":174,"baseurl":"","url":"/p/examples_rclcpp_minimal_composition/github-ros2-examples#ardent","last_commit_time":"2017-12-09","tags":"examples rclcpp minimal composition","name":"examples_rclcpp_minimal_composition","repo_name":"examples","released":"is:released","unreleased":"is:unreleased","version":"0.4.0","description":"Minimalist examples of composing nodes in the same\n  process","maintainers":"Morgan Quigley","authors":"","distro":"ardent","instance":"github-ros2-examples","readme":""},{"id":175,"baseurl":"","url":"/p/examples_rclcpp_minimal_publisher/github-ros2-examples#ardent","last_commit_time":"2017-12-09","tags":"examples rclcpp minimal publisher","name":"examples_rclcpp_minimal_publisher","repo_name":"examples","released":"is:released","unreleased":"is:unreleased","version":"0.4.0","description":"Examples of minimal publisher nodes","maintainers":"Morgan Quigley","authors":"","distro":"ardent","instance":"github-ros2-examples","readme":""},{"id":176,"baseurl":"","url":"/p/examples_rclcpp_minimal_service/github-ros2-examples#ardent","last_commit_time":"2017-12-09","tags":"examples rclcpp minimal service","name":"examples_rclcpp_minimal_service","repo_name":"examples","released":"is:released","unreleased":"is:unreleased","version":"0.4.0","description":"A minimal service server which adds two numbers","maintainers":"Morgan Quigley","authors":"","distro":"ardent","instance":"github-ros2-examples","readme":""},{"id":177,"baseurl":"","url":"/p/examples_rclcpp_minimal_subscriber/github-ros2-examples#ardent","last_commit_time":"2017-12-09","tags":"examples rclcpp minimal subscriber","name":"examples_rclcpp_minimal_subscriber","repo_name":"examples","released":"is:released","unreleased":"is:unreleased","version":"0.4.0","description":"Examples of minimal subscribers","maintainers":"Morgan Quigley","authors":"","distro":"ardent","instance":"github-ros2-examples","readme":""},{"id":178,"baseurl":"","url":"/p/examples_rclcpp_minimal_timer/github-ros2-examples#ardent","last_commit_time":"2017-12-09","tags":"examples rclcpp minimal timer","name":"examples_rclcpp_minimal_timer","repo_name":"examples","released":"is:released","unreleased":"is:unreleased","version":"0.4.0","description":"Examples of minimal nodes which have timers","maintainers":"Morgan Quigley","authors":"","distro":"ardent","instance":"github-ros2-examples","readme":""},{"id":179,"baseurl":"","url":"/p/examples_rclpy_executors/github-ros2-examples#ardent","last_commit_time":"2017-12-09","tags":"examples rclpy executors","name":"examples_rclpy_executors","repo_name":"examples","released":"is:released","unreleased":"is:unreleased","version":"0.4.0","description":"Examples of creating and using exectors to run multiple nodes in the same process","maintainers":"Shane Loretz","authors":"","distro":"ardent","instance":"github-ros2-examples","readme":""},{"id":180,"baseurl":"","url":"/p/examples_rclpy_minimal_client/github-ros2-examples#ardent","last_commit_time":"2017-12-09","tags":"examples rclpy minimal client","name":"examples_rclpy_minimal_client","repo_name":"examples","released":"is:released","unreleased":"is:unreleased","version":"0.4.0","description":"Examples of minimal service clients using rclpy.","maintainers":"Mikael Arguedas","authors":"","distro":"ardent","instance":"github-ros2-examples","readme":""},{"id":181,"baseurl":"","url":"/p/examples_rclpy_minimal_service/github-ros2-examples#ardent","last_commit_time":"2017-12-09","tags":"examples rclpy minimal service","name":"examples_rclpy_minimal_service","repo_name":"examples","released":"is:released","unreleased":"is:unreleased","version":"0.4.0","description":"Examples of minimal service servers using rclpy.","maintainers":"Mikael Arguedas","authors":"","distro":"ardent","instance":"github-ros2-examples","readme":""},{"id":182,"baseurl":"","url":"/p/examples_rclpy_minimal_publisher/github-ros2-examples#ardent","last_commit_time":"2017-12-09","tags":"examples rclpy minimal publisher","name":"examples_rclpy_minimal_publisher","repo_name":"examples","released":"is:released","unreleased":"is:unreleased","version":"0.4.0","description":"Examples of minimal publishers using rclpy.","maintainers":"Mikael Arguedas","authors":"","distro":"ardent","instance":"github-ros2-examples","readme":""},{"id":183,"baseurl":"","url":"/p/examples_rclpy_minimal_subscriber/github-ros2-examples#ardent","last_commit_time":"2017-12-09","tags":"examples rclpy minimal subscriber","name":"examples_rclpy_minimal_subscriber","repo_name":"examples","released":"is:released","unreleased":"is:unreleased","version":"0.4.0","description":"Examples of minimal subscribers using rclpy.","maintainers":"Mikael Arguedas","authors":"","distro":"ardent","instance":"github-ros2-examples","readme":""},{"id":189,"baseurl":"","url":"/p/tf2/github-ros2-geometry2#ardent","last_commit_time":"2017-12-09","tags":"tf2","name":"tf2","repo_name":"geometry2","released":"is:released","unreleased":"is:unreleased","version":"0.8.0","description":"\n    tf2 is the second generation of the transform library, which lets\n    the user keep track of multiple coordinate frames over time. tf2\n    maintains the relationship between coordinate frames in a tree\n    structure buffered in time, and lets the user transform points,\n    vectors, etc between any two coordinate frames at any desired\n    point in time.\n  ","maintainers":"Tully Foote","authors":"Tully Foote Eitan Marder-Eppstein Wim Meeussen","distro":"ardent","instance":"github-ros2-geometry2","readme":""},{"id":190,"baseurl":"","url":"/p/tf2_eigen/github-ros2-geometry2#ardent","last_commit_time":"2017-12-09","tags":"tf2 eigen","name":"tf2_eigen","repo_name":"geometry2","released":"is:released","unreleased":"is:unreleased","version":"0.8.0","description":"tf2_eigen","maintainers":"Koji Terada","authors":"Koji Terada","distro":"ardent","instance":"github-ros2-geometry2","readme":""},{"id":191,"baseurl":"","url":"/p/tf2_geometry_msgs/github-ros2-geometry2#ardent","last_commit_time":"2017-12-09","tags":"tf2 geometry msgs","name":"tf2_geometry_msgs","repo_name":"geometry2","released":"is:released","unreleased":"is:unreleased","version":"0.8.0","description":"\n    tf2_geometry_msgs\n  ","maintainers":"Tully Foote","authors":"Wim Meeussen","distro":"ardent","instance":"github-ros2-geometry2","readme":""},{"id":192,"baseurl":"","url":"/p/tf2_msgs/github-ros2-geometry2#ardent","last_commit_time":"2017-12-09","tags":"tf2 msgs","name":"tf2_msgs","repo_name":"geometry2","released":"is:released","unreleased":"is:unreleased","version":"0.8.0","description":"\n    tf2_msgs\n  ","maintainers":"Tully Foote","authors":"Eitan Marder-Eppstein","distro":"ardent","instance":"github-ros2-geometry2","readme":""},{"id":193,"baseurl":"","url":"/p/tf2_ros/github-ros2-geometry2#ardent","last_commit_time":"2017-12-09","tags":"tf2 ros","name":"tf2_ros","repo_name":"geometry2","released":"is:released","unreleased":"is:unreleased","version":"0.8.0","description":"\n    This package contains the ROS bindings for the tf2 library, for both Python and C++.\n  ","maintainers":"Tully Foote","authors":"Eitan Marder-Eppstein Wim Meeussen","distro":"ardent","instance":"github-ros2-geometry2","readme":""},{"id":196,"baseurl":"","url":"/p/gmock_vendor/github-ament-googletest#ardent","last_commit_time":"2017-08-08","tags":"gmock vendor","name":"gmock_vendor","repo_name":"googletest","released":"is:released","unreleased":"is:unreleased","version":"1.8.0","description":"The package provides GoogleMock.","maintainers":"Dirk Thomas","authors":"","distro":"ardent","instance":"github-ament-googletest","readme":""},{"id":197,"baseurl":"","url":"/p/gtest_vendor/github-ament-googletest#ardent","last_commit_time":"2017-08-08","tags":"gtest vendor","name":"gtest_vendor","repo_name":"googletest","released":"is:released","unreleased":"is:unreleased","version":"1.8.0","description":"The package provides GoogleTest.","maintainers":"Dirk Thomas","authors":"","distro":"ardent","instance":"github-ament-googletest","readme":""},{"id":199,"baseurl":"","url":"/p/joy/github-ros2-joystick_drivers#ardent","last_commit_time":"2017-12-09","tags":"joy","name":"joy","repo_name":"joystick_drivers","released":"is:released","unreleased":"is:unreleased","version":"2.0.0","description":"\n    ROS2 driver for a generic Linux joystick.\n    Will contain a MacOS and Windows version later.\n    The joy package contains joy_node, a node that interfaces a\n    generic Linux joystick to ROS2. This node publishes a \"Joy\"\n    message, which contains the current state of each one of the\n    joystick's buttons and axes.\n  ","maintainers":"Mikael Arguedas","authors":"Morgan Quigley Brian Gerkey Kevin Watts Blaise Gassend Jonathan Bohren","distro":"ardent","instance":"github-ros2-joystick_drivers","readme":""},{"id":201,"baseurl":"","url":"/p/kdl_parser/github-ros2-kdl_parser#ardent","last_commit_time":"2017-12-09","tags":"kdl parser","name":"kdl_parser","repo_name":"kdl_parser","released":"is:released","unreleased":"is:unreleased","version":"2.0.0","description":"\n   The Kinematics and Dynamics Library (KDL) defines a tree structure\n   to represent the kinematic and dynamic parameters of a robot\n   mechanism. ","maintainers":"Chris Lalancette Shane Loretz","authors":"Wim Meeussen Ioan Sucan Jackie Kay","distro":"ardent","instance":"github-ros2-kdl_parser","readme":""},{"id":206,"baseurl":"","url":"/p/launch/github-ros2-launch#ardent","last_commit_time":"2017-12-09","tags":"launch","name":"launch","repo_name":"launch","released":"is:released","unreleased":"is:unreleased","version":"0.4.0","description":"The ROS launch tool.","maintainers":"Dirk Thomas","authors":"","distro":"ardent","instance":"github-ros2-launch","readme":""}]