[{"id":347,"baseurl":"","url":"/p/turtlebot2_amcl/github-ros2-turtlebot2_demo#bouncy","last_commit_time":"2018-07-20","tags":"turtlebot2 amcl","name":"turtlebot2_amcl","repo_name":"turtlebot2_demo","released":"is:released","unreleased":"is:unreleased","version":"0.5.1","description":"Demo of turtlebot2 localization with amcl.","maintainers":"D. Hood","authors":"","distro":"bouncy","instance":"github-ros2-turtlebot2_demo","readme":""},{"id":348,"baseurl":"","url":"/p/turtlebot2_cartographer/github-ros2-turtlebot2_demo#bouncy","last_commit_time":"2018-07-20","tags":"turtlebot2 cartographer","name":"turtlebot2_cartographer","repo_name":"turtlebot2_demo","released":"is:released","unreleased":"is:unreleased","version":"0.5.1","description":"Launch files for turtlebot2 cartographer demo","maintainers":"Chris Lalancette","authors":"","distro":"bouncy","instance":"github-ros2-turtlebot2_demo","readme":""},{"id":349,"baseurl":"","url":"/p/turtlebot2_demo/github-ros2-turtlebot2_demo#bouncy","last_commit_time":"2018-07-20","tags":"turtlebot2 demo","name":"turtlebot2_demo","repo_name":"turtlebot2_demo","released":"is:released","unreleased":"is:unreleased","version":"0.5.1","description":"Metapackage aggregating the turtlebot2 demo packages","maintainers":"Mikael Arguedas","authors":"","distro":"bouncy","instance":"github-ros2-turtlebot2_demo","readme":""},{"id":350,"baseurl":"","url":"/p/turtlebot2_drivers/github-ros2-turtlebot2_demo#bouncy","last_commit_time":"2018-07-20","tags":"turtlebot2 drivers","name":"turtlebot2_drivers","repo_name":"turtlebot2_demo","released":"is:released","unreleased":"is:unreleased","version":"0.5.1","description":"Set of drivers to talk to the kobuki base.","maintainers":"Mikael Arguedas","authors":"Brian Gerkey","distro":"bouncy","instance":"github-ros2-turtlebot2_demo","readme":""},{"id":351,"baseurl":"","url":"/p/turtlebot2_follower/github-ros2-turtlebot2_demo#bouncy","last_commit_time":"2018-07-20","tags":"turtlebot2 follower","name":"turtlebot2_follower","repo_name":"turtlebot2_demo","released":"is:released","unreleased":"is:unreleased","version":"0.5.1","description":"A simple follower using centroid in depth images.","maintainers":"Mikael Arguedas","authors":"Brian Gerkey","distro":"bouncy","instance":"github-ros2-turtlebot2_demo","readme":""},{"id":352,"baseurl":"","url":"/p/turtlebot2_teleop/github-ros2-turtlebot2_demo#bouncy","last_commit_time":"2018-07-20","tags":"turtlebot2 teleop","name":"turtlebot2_teleop","repo_name":"turtlebot2_demo","released":"is:released","unreleased":"is:unreleased","version":"0.5.1","description":"Launch files for turtlebot2 teleop demo","maintainers":"Chris Lalancette","authors":"","distro":"bouncy","instance":"github-ros2-turtlebot2_demo","readme":""},{"id":360,"baseurl":"","url":"/p/uncrustify_vendor/github-ament-uncrustify#bouncy","last_commit_time":"2018-06-28","tags":"uncrustify vendor","name":"uncrustify_vendor","repo_name":"uncrustify","released":"is:released","unreleased":"is:unreleased","version":"0.66.1","description":"\n    Package a newer version of uncrustify (0.61+, b6593c1, April 14th 2015).\n  ","maintainers":"Dirk Thomas","authors":"","distro":"bouncy","instance":"github-ament-uncrustify","readme":""},{"id":362,"baseurl":"","url":"/p/urdf/github-ros2-urdf#bouncy","last_commit_time":"2018-06-25","tags":"urdf","name":"urdf","repo_name":"urdf","released":"is:released","unreleased":"is:unreleased","version":"2.1.0","description":"\n    This package contains a C++ parser for the Unified Robot Description\n    Format (URDF), which is an XML format for representing a robot model.\n    The code API of the parser has been through our review process and will remain\n    backwards compatible in future releases.\n  ","maintainers":"Chris Lalancette Shane Loretz","authors":"Ioan Sucan Jackie Kay","distro":"bouncy","instance":"github-ros2-urdf","readme":""},{"id":364,"baseurl":"","url":"/p/urdfdom/github-ros2-urdfdom#bouncy","last_commit_time":"2018-06-28","tags":"urdfdom","name":"urdfdom","repo_name":"urdfdom","released":"is:released","unreleased":"is:unreleased","version":"2.0.0","description":"A library to access URDFs using the DOM model.","maintainers":"Steven! Ragnarök","authors":"Wim Meeussen John Hsu Ioan Sucan","distro":"bouncy","instance":"github-ros2-urdfdom","readme":""},{"id":366,"baseurl":"","url":"/p/desktop/github-ros2-variants#bouncy","last_commit_time":"2018-07-18","tags":"desktop","name":"desktop","repo_name":"variants","released":"is:released","unreleased":"is:unreleased","version":"0.5.1","description":"A package which extends 'ros_base' and includes high level packages like vizualization tools and demos.","maintainers":"Mikael Arguedas","authors":"","distro":"bouncy","instance":"github-ros2-variants","readme":""},{"id":367,"baseurl":"","url":"/p/ros_base/github-ros2-variants#bouncy","last_commit_time":"2018-07-18","tags":"ros base","name":"ros_base","repo_name":"variants","released":"is:released","unreleased":"is:unreleased","version":"0.5.1","description":"A package which extends 'ros_core' and includes other basic functionalities like tf2 and urdf.","maintainers":"Mikael Arguedas","authors":"","distro":"bouncy","instance":"github-ros2-variants","readme":""},{"id":368,"baseurl":"","url":"/p/ros_core/github-ros2-variants#bouncy","last_commit_time":"2018-07-18","tags":"ros core","name":"ros_core","repo_name":"variants","released":"is:released","unreleased":"is:unreleased","version":"0.5.1","description":"A package to aggregate the packages required to use publish / subscribe, services, generate messages and other core ROS concepts.","maintainers":"Mikael Arguedas","authors":"","distro":"bouncy","instance":"github-ros2-variants","readme":""},{"id":374,"baseurl":"","url":"/p/angles/github-ros-angles#bouncy","last_commit_time":"2018-09-17","tags":"angles","name":"angles","repo_name":"angles","released":"is:released","unreleased":"is:unreleased","version":"1.12.0","description":"This package provides a set of simple math utilities to work\n        with angles. The utilities cover simple things like\n        normalizing an angle and conversion between degrees and\n        radians. But even if you're trying to calculate things like\n        the shortest angular distance between two joint space\n        positions of your robot, but the joint motion is constrained\n        by joint limits, this package is what you need. The code in\n        this package is stable and well tested. There are no plans for\n        major changes in the near future.","maintainers":"Tully Foote","authors":"John Hsu","distro":"bouncy","instance":"github-ros-angles","readme":""},{"id":375,"baseurl":"","url":"/p/ecl_command_line/github-stonier-ecl_core#bouncy","last_commit_time":"2018-09-27","tags":"ecl command line","name":"ecl_command_line","repo_name":"ecl_core","released":"is:released","unreleased":"is:unreleased","version":"1.0.0","description":"\n     Embeds the TCLAP library inside the ecl. This is a very convenient\n     command line parser in templatised c++.\n  ","maintainers":"Daniel Stonier","authors":"Daniel Stonier","distro":"bouncy","instance":"github-stonier-ecl_core","readme":""},{"id":376,"baseurl":"","url":"/p/ecl_concepts/github-stonier-ecl_core#bouncy","last_commit_time":"2018-09-27","tags":"ecl concepts","name":"ecl_concepts","repo_name":"ecl_core","released":"is:released","unreleased":"is:unreleased","version":"1.0.0","description":"\n     Introduces a compile time concept checking mechanism that can be used\n     most commonly to check for required functionality when passing\n     template arguments.\n  ","maintainers":"Daniel Stonier","authors":"Daniel Stonier","distro":"bouncy","instance":"github-stonier-ecl_core","readme":""},{"id":377,"baseurl":"","url":"/p/ecl_containers/github-stonier-ecl_core#bouncy","last_commit_time":"2018-09-27","tags":"ecl containers","name":"ecl_containers","repo_name":"ecl_core","released":"is:released","unreleased":"is:unreleased","version":"1.0.0","description":"\n    The containers included here are intended to extend the stl containers.\n    In all cases, these implementations are designed to implement\n    c++ conveniences and safety where speed is not sacrificed.\n\n    Also includes techniques for memory debugging of common problems such\n    as buffer overruns.\n  ","maintainers":"Daniel Stonier","authors":"Daniel Stonier","distro":"bouncy","instance":"github-stonier-ecl_core","readme":""},{"id":378,"baseurl":"","url":"/p/ecl_converters/github-stonier-ecl_core#bouncy","last_commit_time":"2018-09-27","tags":"ecl converters","name":"ecl_converters","repo_name":"ecl_core","released":"is:released","unreleased":"is:unreleased","version":"1.0.0","description":"\n     Some fast/convenient type converters, mostly for char strings or strings.\n     These are not really fully fleshed out, alot of them could use the addition for\n     the whole range of fundamental types (e.g. all integers, not just int, unsigned int).\n\n     They will come as the need arises.\n  ","maintainers":"Daniel Stonier","authors":"Daniel Stonier","distro":"bouncy","instance":"github-stonier-ecl_core","readme":""},{"id":379,"baseurl":"","url":"/p/ecl_core/github-stonier-ecl_core#bouncy","last_commit_time":"2018-09-27","tags":"ecl core","name":"ecl_core","repo_name":"ecl_core","released":"is:released","unreleased":"is:unreleased","version":"0.61.18","description":"\n    A set of tools and interfaces extending the capabilities of c++ to\n    provide a lightweight, consistent interface with a focus for control\n    programming.\n  ","maintainers":"Daniel Stonier","authors":"Daniel Stonier","distro":"bouncy","instance":"github-stonier-ecl_core","readme":""},{"id":380,"baseurl":"","url":"/p/ecl_core_apps/github-stonier-ecl_core#bouncy","last_commit_time":"2018-09-27","tags":"ecl core apps","name":"ecl_core_apps","repo_name":"ecl_core","released":"is:released","unreleased":"is:unreleased","version":"1.0.0","description":"\n     This includes a suite of programs demo'ing various aspects of the\n     ecl_core. It also includes various benchmarking and utility programs for\n     use primarily with embedded systems.\n  ","maintainers":"Daniel Stonier","authors":"Daniel Stonier","distro":"bouncy","instance":"github-stonier-ecl_core","readme":""},{"id":381,"baseurl":"","url":"/p/ecl_devices/github-stonier-ecl_core#bouncy","last_commit_time":"2018-09-27","tags":"ecl devices","name":"ecl_devices","repo_name":"ecl_core","released":"is:released","unreleased":"is:unreleased","version":"1.0.0","description":"\n     Provides an extensible and standardised framework for input-output devices.\n  ","maintainers":"Daniel Stonier","authors":"Daniel Stonier","distro":"bouncy","instance":"github-stonier-ecl_core","readme":""},{"id":382,"baseurl":"","url":"/p/ecl_eigen/github-stonier-ecl_core#bouncy","last_commit_time":"2018-09-27","tags":"ecl eigen","name":"ecl_eigen","repo_name":"ecl_core","released":"is:released","unreleased":"is:unreleased","version":"1.0.0","description":"\n     This provides an Eigen implementation for ecl's linear algebra.\n  ","maintainers":"Daniel Stonier","authors":"Daniel Stonier","distro":"bouncy","instance":"github-stonier-ecl_core","readme":""},{"id":383,"baseurl":"","url":"/p/ecl_exceptions/github-stonier-ecl_core#bouncy","last_commit_time":"2018-09-27","tags":"ecl exceptions","name":"ecl_exceptions","repo_name":"ecl_core","released":"is:released","unreleased":"is:unreleased","version":"1.0.0","description":"\n     Template based exceptions - these are simple and practical\n     and avoid the proliferation of exception types. Although not\n     syntatactically ideal, it is convenient and eminently practical.\n  ","maintainers":"Daniel Stonier","authors":"Daniel Stonier","distro":"bouncy","instance":"github-stonier-ecl_core","readme":""}]